{"chart":{"result":[{"meta":{"currency":"USD","symbol":"MATIC-USD","exchangeName":"CCC","fullExchangeName":"CCC","instrumentType":"CRYPTOCURRENCY","firstTradeDate":1556409600,"regularMarketTime":1742798820,"hasPrePostMarketData":false,"gmtoffset":0,"timezone":"UTC","exchangeTimezoneName":"UTC","regularMarketPrice":0.21823609,"fiftyTwoWeekHigh":1.083047,"fiftyTwoWeekLow":0.196799,"regularMarketDayHigh":0.21826057,"regularMarketDayLow":0.21034595,"regularMarketVolume":1267171,"longName":"Polygon USD","shortName":"Polygon USD","chartPreviousClose":0.21275991,"priceHint":6,"currentTradingPeriod":{"pre":{"timezone":"UTC","start":1768521600,"end":1768521600,"gmtoffset":0},"regular":{"timezone":"UTC","start":1768521600,"end":1768607940,"gmtoffset":0},"post":{"timezone":"UTC","start":1768607940,"end":1768607940,"gmtoffset":0}},"dataGranularity":"1d","range":"6mo","validRanges":["1d","5d","1mo","3mo","6mo","1y","2y","5y","10y","ytd","max"]},"indicators":{"quote":[{}],"adjclose":[{}]}}],"error":null}}